atalaya/__init__.py
atalaya/logger.py
atalaya/parameters.py
atalaya/grapher/__init__.py
atalaya/grapher/grapher.py
atalaya/grapher/visdom_writer.py
atalaya-0.1.5.4.dist-info/LICENSE
atalaya-0.1.5.4.dist-info/METADATA
atalaya-0.1.5.4.dist-info/WHEEL
atalaya-0.1.5.4.dist-info/top_level.txt
atalaya-0.1.5.4.dist-info/RECORD
