Metadata-Version: 2.1
Name: atalaya
Version: 0.1.5.4
Summary: Atalaya is a logger for pytorch.
Home-page: https://github.com/jacr13/Atalaya
Author: Joao Ramos
Author-email: joao.candido@etu.unige.ch
License: MIT
Platform: UNKNOWN
Requires-Python: >=3.6
Requires-Dist: numpy
Requires-Dist: torch
Requires-Dist: visdom (>=0.1.8.8)
Requires-Dist: tensorboardX (==1.4)
